xenfra_mcp_server/__init__.py
xenfra_mcp_server/__main__.py
xenfra_mcp_server/main.py
xenfra_mcp_server/server.py
xenfra_mcp_server-0.1.3.dist-info/WHEEL
xenfra_mcp_server-0.1.3.dist-info/entry_points.txt
xenfra_mcp_server-0.1.3.dist-info/METADATA
xenfra_mcp_server-0.1.3.dist-info/RECORD
