Metadata-Version: 2.3
Name: xenfra-mcp-server
Version: 0.1.3
Summary: Xenfra Model Context Protocol (MCP) Server - Deploy to DigitalOcean with AI-powered diagnosis.
Author: xenfra-cloud
Author-email: xenfra-cloud <xenfracloud@gmail.com>
Classifier: Programming Language :: Python :: 3
Classifier: License :: OSI Approved :: MIT License
Classifier: Operating System :: OS Independent
Classifier: Development Status :: 3 - Alpha
Classifier: Intended Audience :: Developers
Classifier: Topic :: Software Development :: Build Tools
Classifier: Topic :: System :: Systems Administration
Requires-Dist: mcp>=1.0.0
Requires-Dist: xenfra-sdk>=0.2.3
Requires-Dist: keyring>=24.0.0
Requires-Dist: pytest>=7.0.0 ; extra == 'dev'
Requires-Dist: pytest-asyncio>=0.21.0 ; extra == 'dev'
Requires-Dist: pytest-cov>=4.0.0 ; extra == 'dev'
Requires-Python: >=3.11
Project-URL: Homepage, https://github.com/xenfra-cloud/xenfra-mcp
Project-URL: Issues, https://github.com/xenfra-cloud/xenfra-mcp/issues
Provides-Extra: dev
